<LetterViewer>
  <div class="h-full flex flex-col">
    <LetterInformationViewer />
    <div class="flex-1 shadow-inner bg-gradient-to-b from-slate-200 to-slate-200">
      <div class="w-full h-full relative overflow-auto" style="background-image: url('/grid.png')">
        <div class="absolute w-full">
          <PageEditor />
        </div>
      </div>
    </div>
    <div class="bg-white p-4 shadow-2xl flex justify-between border-t border-solid border-slate-200">
      <div>
        <Button level="'secondary'" icon="'download'">Download PDF</Button>
      </div>
      <div class="flex gap-3">
        <Button icon="'triangle-exclamation'" color="'red'" onClick="() => editor.showBugModal = true">Signal a Problem</Button>
        <Button color="'green'" icon="'floppy-disk'">Save</Button>
        <Button color="'compassion'" icon="'paper-plane'">Submit</Button>
      </div>
    </div>
  </div>
</LetterViewer>